color_matcher/__init__.py
color_matcher/baseclass.py
color_matcher/hist_matcher.py
color_matcher/io_handler.py
color_matcher/mvgd_matcher.py
color_matcher/normalizer.py
color_matcher/top_level.py
color_matcher/bin/cli.py
colour_matcher-0.1.0.data/data/test/data/scotland_house.png
colour_matcher-0.1.0.data/data/test/data/scotland_pitie.png
colour_matcher-0.1.0.data/data/test/data/scotland_plain.png
colour_matcher-0.1.0.data/scripts/cli.py
test/__init__.py
test/frames.py
test/img_downloader.py
test/unit_test.py
test/data/scotland_house.png
test/data/scotland_pitie.png
test/data/scotland_plain.png
colour_matcher-0.1.0.dist-info/LICENSE
colour_matcher-0.1.0.dist-info/METADATA
colour_matcher-0.1.0.dist-info/WHEEL
colour_matcher-0.1.0.dist-info/entry_points.txt
colour_matcher-0.1.0.dist-info/top_level.txt
colour_matcher-0.1.0.dist-info/RECORD
