Metadata-Version: 2.1
Name: colour-matcher
Version: 0.1.0
Summary: Package enabling color transfer across images
Home-page: http://github.com/hahnec/colour-matcher
Author: Christopher Hahne
Author-email: inbox@christopherhahne.de
License: GNU GPL V3.0
Keywords: color match histogram matching image colour transfer monge kantorovich mkl pitie reinhardrecolor re-color recolour re-colour paintings film movie sequence automatic grading color-grading colour-grading equalize equalise equalization equalisation light-field lightfield stop-motion stopmotion
Platform: UNKNOWN
Requires-Python: >=3
Requires-Dist: numpy
Requires-Dist: imageio
Requires-Dist: docutils
